polars_row_collector/__init__.py
polars_row_collector/polars_row_collector.py
polars_row_collector/py.typed
polars_row_collector-0.2.1.dist-info/METADATA
polars_row_collector-0.2.1.dist-info/WHEEL
polars_row_collector-0.2.1.dist-info/licenses/LICENSE
polars_row_collector-0.2.1.dist-info/RECORD
