Metadata-Version: 2.4
Name: polars-row-collector
Version: 0.2.1
Summary: Facade to collect rows one-by-one into a Polars DataFrame (in the least-bad way)
Project-URL: Repository, https://github.com/DeflateAwning/polars-row-collector
Project-URL: Documentation, https://DeflateAwning.github.io/polars-row-collector
Author-email: DeflateAwning <11021263+DeflateAwning@users.noreply.github.com>
License-Expression: MIT
License-File: LICENSE
Classifier: Development Status :: 4 - Beta
Classifier: Intended Audience :: Developers
Classifier: Operating System :: OS Independent
Classifier: Programming Language :: Python
Classifier: Programming Language :: Python :: 3
Classifier: Programming Language :: Python :: 3.11
Classifier: Programming Language :: Python :: 3.12
Classifier: Programming Language :: Python :: 3.13
Classifier: Programming Language :: Python :: 3.14
Classifier: Typing :: Typed
Requires-Python: <4.0,>=3.11
Requires-Dist: polars<2,>=1.0
